{
    "name": "Gokédex, a Notion Intgration with PokéAPI writen in Go",
    "dockerFile": "Dockerfile",
    // "appPort": 8000,
    "customizations": {
        "vscode": {
            "extensions": [
                "golang.Go",
                "davidanson.vscode-markdownlint",
                "shardulm94.trailing-spaces",
                "IBM.output-colorizer",
                "rangav.vscode-thunder-client"
            ],
            "settings": {
                "go.useLanguageServer": true
            }
        }
    },
    "postCreateCommand": "sh ./.devcontainer/install-dev-tools.sh",
    "runArgs": [
        "-u",
        "vscode",
        "--cap-add=SYS_PTRACE",
        "--security-opt",
        "seccomp=unconfined",
        // map SSH keys for Git
        "-v", "${env:HOME}/.ssh:/home/vscode/.ssh:ro"
    ]
}